[[{"Username": ["1PmorchZH8xxKBtN8Ftyio2uiRQXtNU7iD"], "PaidOut": ["0.41488174"], "Balance": [], "UnexchangedBalance": ["0.43656744"], "Rejected": ["15.2300"], "ImmatureUnexchangedBalance": ["0.06297335"], "Accepted": ["687.2507"]},
{"Username": ["1HQyxGKHdrczNuBv9iDuNfrkzX1sS6puv9"], "PaidOut": [], "Balance": [], "UnexchangedBalance": ["0.00302186"], "Rejected": ["2.5911"], "ImmatureUnexchangedBalance": ["0.00532440"], "Accepted": ["81.6118"]},
{"Username": ["1Ly41DnhJrAGesBpykmtcjNSuT9ECFJMG7"], "PaidOut": [], "Balance": [], "UnexchangedBalance": ["0.00338963"], "Rejected": ["1.9946"], "ImmatureUnexchangedBalance": ["0.00580577"], "Accepted": ["79.8409"]},
{"Username": ["15H85MWDDYt4kD8CFA6nzviS8stjTRPZM2"], "PaidOut": [], "Balance": ["0.00049370"], "UnexchangedBalance": ["0.01661070"], "Rejected": ["1.1744"], "ImmatureUnexchangedBalance": ["0.00722408"], "Accepted": ["45.1121"]},
{"Username": ["113GPmSV3P4dFyf7v22d94zynwnEnoJ2c7"], "PaidOut": ["0.06461751"], "Balance": ["0.00010708"], "UnexchangedBalance": ["0.05364075"], "Rejected": ["1.0998"], "ImmatureUnexchangedBalance": ["0.00655469"], "Accepted": ["39.6874"]},
{"Username": ["17TMj9gGaYRtDjcabKfTbRLHbAznXV7U6x"], "PaidOut": ["5.30149626"], "Balance": ["0.00011565"], "UnexchangedBalance": ["0.04811038"], "Rejected": ["0.5965"], "ImmatureUnexchangedBalance": ["0.00302322"], "Accepted": ["35.9778"]},
{"Username": ["1BH6S22coPDFpQJoZXSD5h8oXCmaMdRz31"], "PaidOut": ["0.02508671"], "Balance": ["0.00680335"], "UnexchangedBalance": ["0.01119467"], "Rejected": ["0.0373"], "ImmatureUnexchangedBalance": ["0.00248551"], "Accepted": ["21.5121"]},
{"Username": ["1Bz2D6ek5L2AEhNVreqSK8WTnezpxeuceK"], "PaidOut": ["9.88349878"], "Balance": ["0.00466090"], "UnexchangedBalance": ["0.02616263"], "Rejected": ["0.1678"], "ImmatureUnexchangedBalance": ["0.00358657"], "Accepted": ["19.6480"]},
{"Username": ["1WVZY8nc1eJwkvKSKK1SEN4QtvbwRSR6v"], "PaidOut": ["10.95694581"], "Balance": ["0.00008101"], "UnexchangedBalance": ["0.11378420"], "Rejected": ["0.4474"], "ImmatureUnexchangedBalance": ["0.00306570"], "Accepted": ["18.3804"]},
{"Username": ["17Jr4RMMstbuZNte6AyiR4aChCJxU9hatr"], "PaidOut": ["3.37597264"], "Balance": ["0.00012889"], "UnexchangedBalance": ["0.15531700"], "Rejected": ["0.1491"], "ImmatureUnexchangedBalance": ["0.00296493"], "Accepted": ["18.1380"]},
{"Username": ["1GNEjLM8iYcBwQworC3L4ZzE35nsxWh1eo"], "PaidOut": ["17.13409745"], "Balance": [], "UnexchangedBalance": ["0.11672209"], "Rejected": ["0.5033"], "ImmatureUnexchangedBalance": ["0.00278712"], "Accepted": ["16.6840"]},
{"Username": ["1Bnpo4qKxn5WUrKCkooKMwZ8qJ8ZaXCe2B"], "PaidOut": ["1.79113618"], "Balance": ["0.00005646"], "UnexchangedBalance": ["0.09241032"], "Rejected": ["0.3355"], "ImmatureUnexchangedBalance": ["0.00251722"], "Accepted": ["15.5655"]},
{"Username": ["1PD8iuDp43tib85iYP8jSLJri5PGwVPABr"], "PaidOut": [], "Balance": ["0.00673079"], "UnexchangedBalance": ["0.00309645"], "Rejected": ["0.0746"], "ImmatureUnexchangedBalance": ["0.00072660"], "Accepted": ["14.9131"]},
{"Username": ["18da9fJA1FrGbUqde9u9NC7DeoR9yqhm3W"], "PaidOut": ["0.21175200"], "Balance": [], "UnexchangedBalance": ["0.08276343"], "Rejected": ["0.0373"], "ImmatureUnexchangedBalance": ["0.00977927"], "Accepted": ["14.8944"]},
{"Username": ["1H5ccvgU3V47dBtnjvfrhHjcGG9aJ1ERZf"], "PaidOut": ["0.14537207"], "Balance": ["0.00720446"], "UnexchangedBalance": ["0.08019008"], "Rejected": ["0.0932"], "ImmatureUnexchangedBalance": ["0.00256747"], "Accepted": ["14.8758"]},
{"Username": ["1DncbNpiy3fVM41Sevm8118qEGqtbWzF6x"], "PaidOut": ["0.04813708"], "Balance": ["0.00703230"], "UnexchangedBalance": ["0.03802990"], "Rejected": ["0.1491"], "ImmatureUnexchangedBalance": ["0.00223718"], "Accepted": ["14.4470"]},
{"Username": ["1CEwNiV5xR1e97F7mkJ1gddx8D1JYVuGKW"], "PaidOut": [], "Balance": ["0.00072662"], "UnexchangedBalance": ["0.00814801"], "Rejected": ["0.0559"], "ImmatureUnexchangedBalance": ["0.00235910"], "Accepted": ["14.3166"]},
{"Username": ["1KKd1bp83MngZZheswv3s5KoLFnHJt7YD"], "PaidOut": [], "Balance": [], "UnexchangedBalance": ["0.00047970"], "Rejected": ["0.1305"], "ImmatureUnexchangedBalance": ["0.00092082"], "Accepted": ["13.9251"]},
{"Username": ["15KGTzGZdmJhiGkd1Nw8TaUQRicxL4WF3G"], "PaidOut": ["14.28125776"], "Balance": ["0.00274870"], "UnexchangedBalance": ["0.02103366"], "Rejected": ["0.0559"], "ImmatureUnexchangedBalance": ["0.00217924"], "Accepted": ["13.7760"]},
{"Username": ["18g3ZD7Abb3CrMoYb2PT2YcQ5iC2J21KWa"], "PaidOut": ["0.43419263"], "Balance": ["0.00876787"], "UnexchangedBalance": ["0.08150272"], "Rejected": ["0.0932"], "ImmatureUnexchangedBalance": ["0.00173644"], "Accepted": ["13.4031"]},
{"Username": ["13hfapvCU2Lk7DXQnVirLZEAsK47q5T9vb"], "PaidOut": ["0.94185360"], "Balance": ["0.00888722"], "UnexchangedBalance": ["0.01926815"], "Rejected": ["0.2610"], "ImmatureUnexchangedBalance": ["0.00115530"], "Accepted": ["13.3472"]},
{"Username": ["1CZ3XkKoyEy9iMGGzoi4DSeoQVPsNt9Ywm"], "PaidOut": ["16.55086342"], "Balance": ["0.00586841"], "UnexchangedBalance": ["0.05722033"], "Rejected": ["0.3542"], "ImmatureUnexchangedBalance": ["0.00207705"], "Accepted": ["12.7320"]},
{"Username": ["14DAqUrKatiNZoXYC4SsXTdC45f2jVRYSb"], "PaidOut": ["0.01072960"], "Balance": ["0.00243076"], "UnexchangedBalance": ["0.00042831"], "Rejected": ["0.2796"], "ImmatureUnexchangedBalance": ["0.00070937"], "Accepted": ["11.5204"]},
{"Username": ["1GJFeb6ZJztjLXW8pc1V8GctTGJ2sTidQo"], "PaidOut": [], "Balance": ["0.00573889"], "UnexchangedBalance": ["0.00486236"], "Rejected": ["0.0559"], "ImmatureUnexchangedBalance": ["0.00124575"], "Accepted": ["11.2407"]},
{"Username": ["1AnUiKnKiRkBR8JGnQCGjWserjeRBNr4ZU"], "PaidOut": [], "Balance": [], "UnexchangedBalance": ["0.00172380"], "Rejected": ["0.6152"], "ImmatureUnexchangedBalance": ["0.00098253"], "Accepted": ["10.1409"]},
{"Username": ["171bmRKw96BvMYAng7kUWSSAhMYmqoqmaC"], "PaidOut": ["6.86968299"], "Balance": ["0.00650549"], "UnexchangedBalance": ["0.01557897"], "Rejected": ["0.2983"], "ImmatureUnexchangedBalance": ["0.00084733"], "Accepted": ["9.9918"]},
{"Username": ["13DM4MMEg6RxoAsS3ve7ScZGE9oXq7GkDg"], "PaidOut": ["2.58101658"], "Balance": ["0.00571837"], "UnexchangedBalance": ["0.04546042"], "Rejected": ["0.0186"], "ImmatureUnexchangedBalance": ["0.00129682"], "Accepted": ["9.8986"]},
{"Username": ["19MKMUQperH5gzNJR4fmCwVLTEvJwvVRr5"], "PaidOut": ["1.01764848"], "Balance": ["0.00713727"], "UnexchangedBalance": ["0.06505201"], "Rejected": ["0.2983"], "ImmatureUnexchangedBalance": ["0.00151140"], "Accepted": ["9.4698"]},
{"Username": ["1KcJvM98uiXi8CVA8Kaq67KBWF2xdZmoMK"], "PaidOut": ["3.07344775"], "Balance": ["0.00552051"], "UnexchangedBalance": ["0.05812098"], "Rejected": ["0.3169"], "ImmatureUnexchangedBalance": ["0.00133343"], "Accepted": ["9.3766"]},
{"Username": ["14bEo8ytKVnAhBLhrBJV5BX7SEeZ4CcJZQ"], "PaidOut": ["7.87897138"], "Balance": ["0.00626810"], "UnexchangedBalance": ["0.04960585"], "Rejected": ["0.0373"], "ImmatureUnexchangedBalance": ["0.00141718"], "Accepted": ["9.1715"]},
{"Username": ["1BoPm4sQsPSLBbDLJzNda6GwqG3K2Xir7G"], "PaidOut": ["4.15059254"], "Balance": ["0.00559168"], "UnexchangedBalance": ["0.01210507"], "Rejected": ["0.0186"], "ImmatureUnexchangedBalance": ["0.00074164"], "Accepted": ["8.2208"]},
{"Username": ["1EcvJXNZ9DKfpjW2zMA9UpBpSBQ2UzpK7r"], "PaidOut": ["0.18294583"], "Balance": ["0.00116350"], "UnexchangedBalance": ["0.00488345"], "Rejected": ["0.0186"], "ImmatureUnexchangedBalance": ["0.00072126"], "Accepted": ["6.8787"]},
{"Username": ["1LcRHhGax7rvqzT6Kopo2HbryGkPGEeSMF"], "PaidOut": ["3.93053384"], "Balance": ["0.00728666"], "UnexchangedBalance": ["0.00657614"], "Rejected": ["0.0373"], "ImmatureUnexchangedBalance": ["0.00031893"], "Accepted": ["6.7668"]},
{"Username": ["1JB47vhnuwoHRWwaxicYb64Qu18ZJB4HHP"], "PaidOut": ["0.11377957"], "Balance": ["0.00082273"], "UnexchangedBalance": ["0.00004252"], "Rejected": ["0.0373"], "ImmatureUnexchangedBalance": ["0.00011013"], "Accepted": ["6.7295"]},
{"Username": ["1EdfUKj2awBgqaXz5Dzx9zAQihwGYK7ed9"], "PaidOut": ["3.32364785"], "Balance": ["0.00001246"], "UnexchangedBalance": ["0.03021114"], "Rejected": ["0.2610"], "ImmatureUnexchangedBalance": ["0.00100104"], "Accepted": ["6.6177"]},
{"Username": ["16xdMgHVj9TLyaE9nD1soJGMnugUg18eCX"], "PaidOut": ["4.88728312"], "Balance": ["0.00425798"], "UnexchangedBalance": ["0.04197591"], "Rejected": ["0.2983"], "ImmatureUnexchangedBalance": ["0.00102525"], "Accepted": ["6.5804"]},
{"Username": ["1G8sxxXngaAzhmTyYkr6dRcgNsAwopWCxo"], "PaidOut": ["0.65855306"], "Balance": ["0.00503414"], "UnexchangedBalance": ["0.05065857"], "Rejected": ["0.2237"], "ImmatureUnexchangedBalance": ["0.00121807"], "Accepted": ["6.5804"]},
{"Username": ["1L4oCGYFGTbJBGbvmJidckHzQ4EnEJFsxs"], "PaidOut": [], "Balance": ["0.00004271"], "UnexchangedBalance": ["0.00005472"], "Rejected": [], "ImmatureUnexchangedBalance": ["0.00012116"], "Accepted": ["6.4872"]},
{"Username": ["1LqeEJc8sSogV9QwaL3zB2bFQYidpvaRVo"], "PaidOut": ["2.99216773"], "Balance": ["0.00456008"], "UnexchangedBalance": ["0.01057271"], "Rejected": ["0.0186"], "ImmatureUnexchangedBalance": ["0.00057301"], "Accepted": ["6.1889"]},
{"Username": ["17wjHBTYcz4gHvvpVCVVPLbbdTNiSFv2ar"], "PaidOut": ["3.69103472"], "Balance": ["0.00469135"], "UnexchangedBalance": ["0.03534869"], "Rejected": [], "ImmatureUnexchangedBalance": ["0.00085533"], "Accepted": ["5.8534"]},
{"Username": ["1BcpGreCimbWXmYBKpr6tQ1TWHofP1WVa3"], "PaidOut": ["0.03426011"], "Balance": ["0.00237688"], "UnexchangedBalance": ["0.02542035"], "Rejected": [], "ImmatureUnexchangedBalance": ["0.00089206"], "Accepted": ["5.8161"]},
{"Username": ["124t7FN57Cp7AWfnZBso1tYgZf23LL62vW"], "PaidOut": [], "Balance": ["0.00786773"], "UnexchangedBalance": ["0.00507628"], "Rejected": ["0.0746"], "ImmatureUnexchangedBalance": ["0.00087845"], "Accepted": ["5.4433"]},
{"Username": ["12H8RGCcNeZ8AndWJbdx58p1kyAiLRqg57"], "PaidOut": ["0.08283740"], "Balance": ["0.00768034"], "UnexchangedBalance": ["0.01229381"], "Rejected": ["0.1678"], "ImmatureUnexchangedBalance": ["0.00083208"], "Accepted": ["5.4246"]},
{"Username": ["1Pkhbe74itCBm2kVAcHfki4YoRgrTaLrjY"], "PaidOut": ["1.84218502"], "Balance": ["0.00318689"], "UnexchangedBalance": ["0.03043332"], "Rejected": ["0.1305"], "ImmatureUnexchangedBalance": ["0.00091463"], "Accepted": ["5.3501"]},
{"Username": ["1BkdFFjGtoPerfq9x5w7ek8mg8faJpMbAC"], "PaidOut": ["3.45249630"], "Balance": ["0.00403517"], "UnexchangedBalance": ["0.00840147"], "Rejected": ["0.0932"], "ImmatureUnexchangedBalance": ["0.00050329"], "Accepted": ["5.3314"]},
{"Username": ["14mnvmg8Hcjs1EZ7dhbw14hpetmYpPZ2Ew"], "PaidOut": ["1.21226071"], "Balance": ["0.00398898"], "UnexchangedBalance": ["0.03417607"], "Rejected": ["0.0746"], "ImmatureUnexchangedBalance": ["0.00088520"], "Accepted": ["5.2755"]},
{"Username": ["1HBeWxujnLAsUyQ4sejroTKqxC1nBoTacX"], "PaidOut": ["0.18181986"], "Balance": ["0.00987750"], "UnexchangedBalance": ["0.00144304"], "Rejected": [], "ImmatureUnexchangedBalance": ["0.00053475"], "Accepted": ["5.2755"]},
{"Username": ["1MCbtGN9VAS2d3gevRbCZCL61LX3NHHBWm"], "PaidOut": ["0.78879870"], "Balance": ["0.00145479"], "UnexchangedBalance": ["0.01152961"], "Rejected": ["0.0186"], "ImmatureUnexchangedBalance": ["0.00085573"], "Accepted": ["5.1450"]},
{"Username": ["1HAgiAsa9apY8A72topqu5db3HDqyBT1UT"], "PaidOut": ["0.09996760"], "Balance": ["0.00989911"], "UnexchangedBalance": ["0.02306451"], "Rejected": ["0.0186"], "ImmatureUnexchangedBalance": ["0.00087581"], "Accepted": ["4.9772"]},
{"Username": ["16pU6BZzRnu45pMHjs2UR7RfeM3RDP22nu"], "PaidOut": ["0.09449712"], "Balance": ["0.00348729"], "UnexchangedBalance": ["0.03235592"], "Rejected": ["0.0186"], "ImmatureUnexchangedBalance": ["0.00074357"], "Accepted": ["4.9586"]},
{"Username": ["17kSS6k7tW2JNMHQdUsRS58Cu6dbmgWQ5w"], "PaidOut": ["1.13890419"], "Balance": ["0.00001441"], "UnexchangedBalance": ["0.03072102"], "Rejected": ["0.0373"], "ImmatureUnexchangedBalance": ["0.00077202"], "Accepted": ["4.9027"]},
{"Username": ["173uwjJnhvnPDdxcxAsRB81orqZCbyrofu"], "PaidOut": ["2.58767493"], "Balance": ["0.00323420"], "UnexchangedBalance": ["0.00114356"], "Rejected": ["0.0186"], "ImmatureUnexchangedBalance": ["0.00004020"], "Accepted": ["4.8095"]},
{"Username": ["18MhjkU2EEfbhB76671ZxipePUGofsWgyd"], "PaidOut": ["5.27831969"], "Balance": ["0.00487450"], "UnexchangedBalance": ["0.03583478"], "Rejected": ["0.0559"], "ImmatureUnexchangedBalance": ["0.00080622"], "Accepted": ["4.7349"]},
{"Username": ["1ZtTJezgqQKi1y5qpcBuGCfPe5GNNw4GV"], "PaidOut": ["3.87776380"], "Balance": ["0.00001547"], "UnexchangedBalance": ["0.02426399"], "Rejected": ["0.1118"], "ImmatureUnexchangedBalance": ["0.00073813"], "Accepted": ["4.6976"]},
{"Username": ["1MiSKxT6pCA9QCP5Leb3sFCB2aqxiz16Nv"], "PaidOut": ["3.02840859"], "Balance": ["0.00483655"], "UnexchangedBalance": ["0.04517076"], "Rejected": ["0.0186"], "ImmatureUnexchangedBalance": ["0.00075594"], "Accepted": ["4.6603"]},
{"Username": ["1NQWrstsi4JrY6YdjqhJAkARiGgW85KB7b"], "PaidOut": ["1.18635828"], "Balance": ["0.00392615"], "UnexchangedBalance": ["0.03304288"], "Rejected": ["0.0186"], "ImmatureUnexchangedBalance": ["0.00081552"], "Accepted": ["4.6231"]},
{"Username": ["1QChspeSuNyoApJ8ZJiQgCS7Cs9zZDVKCt"], "PaidOut": ["4.88168702"], "Balance": ["0.00336428"], "UnexchangedBalance": ["0.03040563"], "Rejected": ["0.0559"], "ImmatureUnexchangedBalance": ["0.00074074"], "Accepted": ["4.4926"]},
{"Username": ["1KYjppWHtAgzpvBDTGFRzcUEnyhK3jzuiN"], "PaidOut": ["15.34167491"], "Balance": [], "UnexchangedBalance": ["0.02285074"], "Rejected": ["0.0746"], "ImmatureUnexchangedBalance": ["0.00069948"], "Accepted": ["4.4739"]},
{"Username": ["1FxYJXejFiTDUTgDgot2mxL9oiUV2Z7GDP"], "PaidOut": ["2.33279570"], "Balance": ["0.00240909"], "UnexchangedBalance": ["0.02493589"], "Rejected": ["0.0373"], "ImmatureUnexchangedBalance": ["0.00075716"], "Accepted": ["4.4366"]},
{"Username": ["1M8hwo1fpfPgM8FXQtcaYxniQBA9bGA4fr"], "PaidOut": ["1.65352400"], "Balance": ["0.00363054"], "UnexchangedBalance": ["0.03200402"], "Rejected": ["0.0932"], "ImmatureUnexchangedBalance": ["0.00069009"], "Accepted": ["4.3434"]},
{"Username": ["1ARMDXVSWLeYH3HkX5nGMUztY8AJqMzmBt"], "PaidOut": ["8.02371758"], "Balance": ["0.00421212"], "UnexchangedBalance": ["0.04114936"], "Rejected": ["0.1491"], "ImmatureUnexchangedBalance": ["0.00070531"], "Accepted": ["4.2129"]},
{"Username": ["13fGYvprvfXjaJKLpnhXXiCQyzzynuA4oX"], "PaidOut": ["1.21586438"], "Balance": ["0.00001441"], "UnexchangedBalance": ["0.00488636"], "Rejected": [], "ImmatureUnexchangedBalance": ["0.00032368"], "Accepted": ["4.1570"]},
{"Username": ["1MXM1qhmkzppuTroMeEpeqYr9WmEc8mCuG"], "PaidOut": ["0.76073643"], "Balance": ["0.00805424"], "UnexchangedBalance": ["0.00532196"], "Rejected": ["0.0932"], "ImmatureUnexchangedBalance": ["0.00030118"], "Accepted": ["3.9706"]},
{"Username": ["1PzpH8JXbMkg1Ttyps4f6WDqqXRV8khLBX"], "PaidOut": ["4.19364361"], "Balance": ["0.00002062"], "UnexchangedBalance": ["0.02867378"], "Rejected": ["0.0559"], "ImmatureUnexchangedBalance": ["0.00069106"], "Accepted": ["3.9333"]},
{"Username": ["19GiYXMCefChK5Ffy7fZenRrSvgXBpBEzx"], "PaidOut": ["1.94439091"], "Balance": ["0.00001051"], "UnexchangedBalance": ["0.00601734"], "Rejected": ["0.0186"], "ImmatureUnexchangedBalance": ["0.00035171"], "Accepted": ["3.8960"]},
{"Username": ["1PsojT59cWEKrFDNcHK6hvZk1jRWq6cw39"], "PaidOut": ["0.88916360"], "Balance": ["0.00970734"], "UnexchangedBalance": ["0.01498272"], "Rejected": ["0.0559"], "ImmatureUnexchangedBalance": ["0.00064818"], "Accepted": ["3.7842"]},
{"Username": ["1EtgoAQ4NUSfPbtcBz2aTvfYELrxTbgSKP"], "PaidOut": [], "Balance": ["0.00463855"], "UnexchangedBalance": ["0.00432922"], "Rejected": ["0.0186"], "ImmatureUnexchangedBalance": ["0.00065615"], "Accepted": ["3.7842"]},
{"Username": ["1M66sMrABxgbfcEH47wTqCYKk7NKVh21Y1"], "PaidOut": ["12.55520653"], "Balance": ["0.00205555"], "UnexchangedBalance": ["0.01961308"], "Rejected": [], "ImmatureUnexchangedBalance": ["0.00056734"], "Accepted": ["3.7283"]},
{"Username": ["1PeeyH8g5acT8Xqvy2QxXS2etCSgtGeLcj"], "PaidOut": ["0.39312056"], "Balance": ["0.00827107"], "UnexchangedBalance": ["0.02419217"], "Rejected": ["0.0186"], "ImmatureUnexchangedBalance": ["0.00062568"], "Accepted": ["3.7096"]},
{"Username": ["17qyak2UnByqnhUgx62VwbLYJLT8pxR2w4"], "PaidOut": ["1.30713463"], "Balance": ["0.00001051"], "UnexchangedBalance": ["0.00827098"], "Rejected": ["0.0186"], "ImmatureUnexchangedBalance": ["0.00057817"], "Accepted": ["3.6910"]},
{"Username": ["19aaJ7VdvCsvXmZRf3Ja5PxRJicPZ7neYs"], "PaidOut": ["0.26487222"], "Balance": ["0.00295057"], "UnexchangedBalance": ["0.02646494"], "Rejected": ["0.1678"], "ImmatureUnexchangedBalance": ["0.00066482"], "Accepted": ["3.5791"]},
{"Username": ["1JjKw1DYfacKnThn3h146xnLe8AyPPHNrN"], "PaidOut": ["5.64561319"], "Balance": ["0.00310649"], "UnexchangedBalance": ["0.03597535"], "Rejected": [], "ImmatureUnexchangedBalance": ["0.00054337"], "Accepted": ["3.5046"]},
{"Username": ["1NL9byDk96VYWinPhuz6bN7ETH9dp9G8Va"], "PaidOut": ["1.00114893"], "Balance": ["0.00896922"], "UnexchangedBalance": ["0.02355698"], "Rejected": ["0.0186"], "ImmatureUnexchangedBalance": ["0.00061005"], "Accepted": ["3.4673"]},
{"Username": ["1G6ctkcaY9SAa8fr3KWr9gjrbuzXF6Qr3p"], "PaidOut": ["0.17285549"], "Balance": [], "UnexchangedBalance": ["0.01773909"], "Rejected": ["0.0746"], "ImmatureUnexchangedBalance": ["0.00057490"], "Accepted": ["3.4486"]},
{"Username": ["151ZTjqLoR6w7kiPnvXReT5pznsF3PNr3U"], "PaidOut": ["1.22511509"], "Balance": ["0.00001246"], "UnexchangedBalance": ["0.02110802"], "Rejected": [], "ImmatureUnexchangedBalance": ["0.00051414"], "Accepted": ["3.3927"]},
{"Username": ["19p92BstweyFdkkrAAjQFDp5atziZt1Vzp"], "PaidOut": ["0.15210002"], "Balance": ["0.00586535"], "UnexchangedBalance": ["0.00265640"], "Rejected": [], "ImmatureUnexchangedBalance": ["0.00018188"], "Accepted": ["3.3927"]},
{"Username": ["19p42d6e7q5XUqcERwYbM9RXEXdp86UCyR"], "PaidOut": ["1.00951159"], "Balance": ["0.00420374"], "UnexchangedBalance": ["0.03909247"], "Rejected": [], "ImmatureUnexchangedBalance": ["0.00057941"], "Accepted": ["3.3368"]},
{"Username": ["1SKpKtzVC1Ge9x6zBCqQH1uhfCiUnx5gk"], "PaidOut": ["1.17895822"], "Balance": ["0.00955277"], "UnexchangedBalance": ["0.02589056"], "Rejected": ["0.0186"], "ImmatureUnexchangedBalance": ["0.00057647"], "Accepted": ["3.2622"]},
{"Username": ["1AJ4gJBDERgS5ceWkXFwADFfgpfW7oQvo3"], "PaidOut": ["0.84955416"], "Balance": ["0.00357252"], "UnexchangedBalance": ["0.03110750"], "Rejected": ["0.2423"], "ImmatureUnexchangedBalance": ["0.00066331"], "Accepted": ["3.2622"]},
{"Username": ["19QTy63jTfCQpjQGDQr95aLSefFdV6UsAR"], "PaidOut": ["0.45925541"], "Balance": ["0.00717386"], "UnexchangedBalance": ["0.01385699"], "Rejected": ["0.0373"], "ImmatureUnexchangedBalance": ["0.00050978"], "Accepted": ["3.2436"]},
{"Username": ["1KVZjMC88KKBF39UbCqg7CALSmzKYWsiiy"], "PaidOut": [], "Balance": [], "UnexchangedBalance": ["0.00003194"], "Rejected": [], "ImmatureUnexchangedBalance": ["0.00007251"], "Accepted": ["3.2250"]},
{"Username": ["1FXr4mzEKVAahFuD2qu26xKToEsPEyNqPa"], "PaidOut": [], "Balance": ["0.00244952"], "UnexchangedBalance": ["0.00306505"], "Rejected": [], "ImmatureUnexchangedBalance": ["0.00054132"], "Accepted": ["3.1690"]},
{"Username": ["16e8sGhzEYzSmjRWu5DGcB2XsLwTbJKbXd"], "PaidOut": ["5.40327478"], "Balance": ["0.00558436"], "UnexchangedBalance": ["0.00523546"], "Rejected": ["0.0373"], "ImmatureUnexchangedBalance": ["0.00028289"], "Accepted": ["3.1317"]},
{"Username": ["1GR4vX31EzAZ3SSyYxuYf5ArWT4kY2L4Wk"], "PaidOut": ["1.87371269"], "Balance": [], "UnexchangedBalance": ["0.14026881"], "Rejected": [], "ImmatureUnexchangedBalance": ["0.00051905"], "Accepted": ["3.1131"]},
{"Username": ["19QJWCQwQ1xw4x9ibf2gwPW5idtgbmjX2e"], "PaidOut": ["5.10783333"], "Balance": ["0.00150927"], "UnexchangedBalance": ["0.01552823"], "Rejected": ["0.1305"], "ImmatureUnexchangedBalance": ["0.00053412"], "Accepted": ["3.0945"]},
{"Username": ["122Z69LaD9W8rVFogexSf51o9d9buu2eJg"], "PaidOut": ["0.98541820"], "Balance": ["0.00825663"], "UnexchangedBalance": ["0.01807218"], "Rejected": ["0.0186"], "ImmatureUnexchangedBalance": ["0.00045424"], "Accepted": ["3.0572"]},
{"Username": ["1E7UprHgz3yMaP7CrPdA3XFKC8okrgYREW"], "PaidOut": ["4.08704504"], "Balance": ["0.00826550"], "UnexchangedBalance": ["0.01892875"], "Rejected": ["0.0559"], "ImmatureUnexchangedBalance": ["0.00045029"], "Accepted": ["3.0013"]},
{"Username": ["1PKjVoi9gKHXsKqgPxMJ1WL3MrHApGtCKz"], "PaidOut": ["5.67239755"], "Balance": ["0.00491998"], "UnexchangedBalance": ["0.00430850"], "Rejected": ["0.0746"], "ImmatureUnexchangedBalance": ["0.00024098"], "Accepted": ["2.9267"]},
{"Username": ["138RvrfefmYgE7FAYHfpthJ7A8k8Tt2KYc"], "PaidOut": [], "Balance": ["0.00009412"], "UnexchangedBalance": ["0.00020272"], "Rejected": ["0.0186"], "ImmatureUnexchangedBalance": ["0.00024200"], "Accepted": ["2.9267"]},
{"Username": ["1D2jbyJAmxW9GCgvsVcFB33GpPJHvbPHVr"], "PaidOut": ["1.09367562"], "Balance": ["0.00882924"], "UnexchangedBalance": ["0.00371609"], "Rejected": ["0.0932"], "ImmatureUnexchangedBalance": ["0.00039340"], "Accepted": ["2.9081"]},
{"Username": ["1AE4bEdz6bpWSLMn7rkAUrXXwt3YXE8nbU"], "PaidOut": ["1.05030683"], "Balance": ["0.00001441"], "UnexchangedBalance": ["0.02154238"], "Rejected": ["0.0186"], "ImmatureUnexchangedBalance": ["0.00050702"], "Accepted": ["2.8708"]},
{"Username": ["1LFZZJ6nmdRojHAjAYfkChtxhuFjoJ2yHi"], "PaidOut": [], "Balance": ["0.00222915"], "UnexchangedBalance": ["0.00192014"], "Rejected": ["0.0559"], "ImmatureUnexchangedBalance": ["0.00048666"], "Accepted": ["2.8335"]},
{"Username": ["1ETaVXkopRwEuRvsk9xYqwtvSEAaTXFvN1"], "PaidOut": ["2.28365427"], "Balance": ["0.00134502"], "UnexchangedBalance": ["0.01165063"], "Rejected": [], "ImmatureUnexchangedBalance": ["0.00036904"], "Accepted": ["2.7962"]},
{"Username": ["1HWocB4cBYYrMwFLg7foXNUp3NAzjVJ5qd"], "PaidOut": ["1.90567727"], "Balance": ["0.00163403"], "UnexchangedBalance": ["0.00351062"], "Rejected": ["0.0373"], "ImmatureUnexchangedBalance": ["0.00021144"], "Accepted": ["2.7962"]},
{"Username": ["16Tfm9TYLcd7CBU8T5cD1p22pcUgkFFCM2"], "PaidOut": ["0.03166740"], "Balance": ["0.00503354"], "UnexchangedBalance": ["0.00603130"], "Rejected": ["0.0932"], "ImmatureUnexchangedBalance": ["0.00042712"], "Accepted": ["2.7962"]},
{"Username": ["1N3pYZJhkM5P2m5oPA2kWnYbGSTFYVd8ST"], "PaidOut": ["3.01343385"], "Balance": [], "UnexchangedBalance": ["0.01756771"], "Rejected": ["0.0559"], "ImmatureUnexchangedBalance": ["0.00039362"], "Accepted": ["2.7403"]},
{"Username": ["13mcNytqiKinxVG8XvyY6AtVfaZQ8DyGkN"], "PaidOut": [], "Balance": ["0.00002747"], "UnexchangedBalance": ["0.00125263"], "Rejected": ["0.0186"], "ImmatureUnexchangedBalance": ["0.00048084"], "Accepted": ["2.7403"]},
{"Username": ["1Gfgv6gDwsQBasomxE5TqRETZ6ZdiFGzzE"], "PaidOut": ["0.84837979"], "Balance": ["0.00210016"], "UnexchangedBalance": ["0.01953833"], "Rejected": ["0.0186"], "ImmatureUnexchangedBalance": ["0.00044093"], "Accepted": ["2.6657"]},
{"Username": ["1BSPnbtDYTozV6gxuSiK4D2uV1ojo2LZtw"], "PaidOut": ["0.75411580"], "Balance": ["0.00986079"], "UnexchangedBalance": ["0.01383681"], "Rejected": ["0.0746"], "ImmatureUnexchangedBalance": ["0.00037391"], "Accepted": ["2.6657"]},
{"Username": ["125qxUSpXuyAJYs5gZ1mdGhQjhZgAsWaba"], "PaidOut": ["1.18538323"], "Balance": ["0.00000896"], "UnexchangedBalance": ["0.02064271"], "Rejected": ["0.0746"], "ImmatureUnexchangedBalance": ["0.00046478"], "Accepted": ["2.6471"]},
{"Username": ["17mJDarb626zcoaD4RhzKo6PUoeQUgk5EH"], "PaidOut": ["3.63675977"], "Balance": ["0.00377695"], "UnexchangedBalance": ["0.02919796"], "Rejected": [], "ImmatureUnexchangedBalance": ["0.00055997"], "Accepted": ["2.6284"]},
{"Username": ["1C2udXGDZn5GmaqtEoxQ9DbGA9r7PK4wen"], "PaidOut": ["0.90915537"], "Balance": ["0.00830962"], "UnexchangedBalance": ["0.01897506"], "Rejected": ["0.0559"], "ImmatureUnexchangedBalance": ["0.00043994"], "Accepted": ["2.6098"]},
{"Username": ["1BnuceiH7P68HRSNBsfUzNs2biroeDMf1x"], "PaidOut": ["3.08667949"], "Balance": ["0.00999400"], "UnexchangedBalance": ["0.01933219"], "Rejected": ["0.0186"], "ImmatureUnexchangedBalance": ["0.00046842"], "Accepted": ["2.5725"]},
{"Username": ["13HDefAfwzGp5ebCGK3F3htKVbtRPwJZnc"], "PaidOut": ["0.32929778"], "Balance": ["0.00946797"], "UnexchangedBalance": ["0.01396072"], "Rejected": ["0.0373"], "ImmatureUnexchangedBalance": ["0.00043443"], "Accepted": ["2.5352"]},
{"Username": ["1JBJ4ktxtXuxLis2spTDmhPaUzbQeeJD2o"], "PaidOut": ["2.16233299"], "Balance": ["0.00180575"], "UnexchangedBalance": ["0.00374058"], "Rejected": ["0.1118"], "ImmatureUnexchangedBalance": ["0.00021937"], "Accepted": ["2.5166"]},
{"Username": ["1BWm62KWj23441Dp2ERXCrm3vYGMZPVnhf"], "PaidOut": ["1.02221723"], "Balance": ["0.00144764"], "UnexchangedBalance": ["0.00335990"], "Rejected": ["0.0186"], "ImmatureUnexchangedBalance": ["0.00020131"], "Accepted": ["2.4979"]},
{"Username": ["17ASfA37SqN2dK6JmNqXKV3ShQQY1N6xu6"], "PaidOut": ["0.68201892"], "Balance": ["0.00162643"], "UnexchangedBalance": ["0.01185626"], "Rejected": ["0.0373"], "ImmatureUnexchangedBalance": ["0.00033797"], "Accepted": ["2.4979"]},
{"Username": ["13ZPHDx4CqeCyqBoamo5JQdBq9yh1FKDQX"], "PaidOut": ["0.92990088"], "Balance": ["0.00001752"], "UnexchangedBalance": ["0.01805010"], "Rejected": [], "ImmatureUnexchangedBalance": ["0.00043699"], "Accepted": ["2.4793"]},
{"Username": ["1GKCkSjn3sXovNDe1NxXmenz8ZZ97fceYd"], "PaidOut": ["0.86275682"], "Balance": ["0.00528273"], "UnexchangedBalance": ["0.01416593"], "Rejected": ["0.0186"], "ImmatureUnexchangedBalance": ["0.00034100"], "Accepted": ["2.4793"]},
{"Username": ["1EpsCNT5HcXERxeu9R61bBr5nEk1rVkKMF"], "PaidOut": ["1.54561724"], "Balance": ["0.00000765"], "UnexchangedBalance": ["0.00310302"], "Rejected": ["0.0186"], "ImmatureUnexchangedBalance": ["0.00021189"], "Accepted": ["2.4420"]},
{"Username": ["1ABg4Y4JfeeZmYM5ToaXBroTboshxAD1ow"], "PaidOut": ["0.40604594"], "Balance": ["0.00163448"], "UnexchangedBalance": ["0.01545574"], "Rejected": [], "ImmatureUnexchangedBalance": ["0.00035915"], "Accepted": ["2.4047"]},
{"Username": ["13fbggrKyRMLdQqLxnkpqsniHM4PXkkcat"], "PaidOut": ["1.34355973"], "Balance": ["0.00001207"], "UnexchangedBalance": ["0.00424212"], "Rejected": ["0.1305"], "ImmatureUnexchangedBalance": ["0.00020981"], "Accepted": ["2.3861"]},
{"Username": ["1MUUJPoRsiSc7pqRoxzsqJnRxqG11vnFhN"], "PaidOut": ["1.15509542"], "Balance": ["0.00162513"], "UnexchangedBalance": ["0.01541744"], "Rejected": [], "ImmatureUnexchangedBalance": ["0.00037351"], "Accepted": ["2.3861"]},
{"Username": ["1FgTw1b2Q3w9GcxM2xm2b3wBa779Ukuwx1"], "PaidOut": ["1.78900667"], "Balance": ["0.00716971"], "UnexchangedBalance": ["0.01934466"], "Rejected": [], "ImmatureUnexchangedBalance": ["0.00033665"], "Accepted": ["2.3675"]},
{"Username": ["1F4fn9wEomMnke6jqASkpqiA98E1yiva93"], "PaidOut": ["2.52776473"], "Balance": ["0.00788373"], "UnexchangedBalance": ["0.00856527"], "Rejected": ["0.0186"], "ImmatureUnexchangedBalance": ["0.00023403"], "Accepted": ["2.3488"]},
{"Username": ["16UhShJEvphYWCXEyCmjTu9eWiXWz9ZLke"], "PaidOut": ["6.99245961"], "Balance": ["0.00884909"], "UnexchangedBalance": ["0.01641595"], "Rejected": ["0.0373"], "ImmatureUnexchangedBalance": ["0.00038830"], "Accepted": ["2.3115"]},
{"Username": ["1QDLYyiSS1wK2JZd4dGbETSTZAXBQ8CgE1"], "PaidOut": ["1.06305034"], "Balance": ["0.00171550"], "UnexchangedBalance": ["0.01212881"], "Rejected": ["0.0559"], "ImmatureUnexchangedBalance": ["0.00027841"], "Accepted": ["2.3115"]},
{"Username": ["17Xa8ckXdEw9uLpjUzd2LUiKvYhPXGZxdt"], "PaidOut": [], "Balance": ["0.00618641"], "UnexchangedBalance": ["0.00422205"], "Rejected": ["0.0186"], "ImmatureUnexchangedBalance": ["0.00031326"], "Accepted": ["2.3115"]},
{"Username": ["1HhnMLZHCPZQ6VU7yDt369mf3zJzP4wcZu"], "PaidOut": ["0.01015169"], "Balance": ["0.00070553"], "UnexchangedBalance": ["0.00863859"], "Rejected": [], "ImmatureUnexchangedBalance": ["0.00025141"], "Accepted": ["2.2929"]},
{"Username": ["12sdTVh8gnKWsMU77rA7PqsqUWFxApSoqZ"], "PaidOut": ["0.41997003"], "Balance": ["0.00178083"], "UnexchangedBalance": ["0.01731765"], "Rejected": ["0.0373"], "ImmatureUnexchangedBalance": ["0.00040349"], "Accepted": ["2.2742"]},
{"Username": ["1EFSNcqhAyGDBfEeAmpneiK98b2qGmoTaV"], "PaidOut": ["25.41657145"], "Balance": ["0.00089064"], "UnexchangedBalance": ["0.00014991"], "Rejected": ["0.0186"], "ImmatureUnexchangedBalance": ["0.00013976"], "Accepted": ["2.2370"]},
{"Username": ["13ukB4jL5CTdEdBEJ1P8XyMHtF3rbQE9bw"], "PaidOut": ["4.90032764"], "Balance": ["0.00935147"], "UnexchangedBalance": ["0.00349145"], "Rejected": ["0.0373"], "ImmatureUnexchangedBalance": ["0.00017642"], "Accepted": ["2.2370"]},
{"Username": ["15Q29M1Xq12j4LYQhpLWMmpMujR4ydajZD"], "PaidOut": ["2.51609001"], "Balance": ["0.00654156"], "UnexchangedBalance": ["0.00251782"], "Rejected": ["0.0746"], "ImmatureUnexchangedBalance": ["0.00030633"], "Accepted": ["2.2370"]},
{"Username": ["1EeEACUVejZdbimkVZadMEccBcRPP6fP5j"], "PaidOut": ["1.61023515"], "Balance": ["0.00176649"], "UnexchangedBalance": ["0.01695307"], "Rejected": ["0.1305"], "ImmatureUnexchangedBalance": ["0.00039230"], "Accepted": ["2.2370"]},
{"Username": ["1J8YHYct2KSC7gGCamMp5ZkRgmZUwq16ef"], "PaidOut": ["4.26668961"], "Balance": [], "UnexchangedBalance": ["0.02416412"], "Rejected": ["0.0186"], "ImmatureUnexchangedBalance": ["0.00044030"], "Accepted": ["2.2183"]},
{"Username": ["1TZpxriiM9AWaAUdyWbjazXzC1KKG6eL2"], "PaidOut": ["1.76110130"], "Balance": ["0.00200097"], "UnexchangedBalance": ["0.01629767"], "Rejected": [], "ImmatureUnexchangedBalance": ["0.00039279"], "Accepted": ["2.2183"]},
{"Username": ["16XLiiGt49YX4MMoDT99eKcbxaRyEbC2q8"], "PaidOut": ["1.18467367"], "Balance": ["0.00000779"], "UnexchangedBalance": ["0.00330535"], "Rejected": ["0.0186"], "ImmatureUnexchangedBalance": ["0.00019751"], "Accepted": ["2.2183"]},
{"Username": ["1My2NdqGDuufNqkXWvso6mPQsi7Ki8aEAA"], "PaidOut": ["0.76286818"], "Balance": ["0.00182816"], "UnexchangedBalance": ["0.01565097"], "Rejected": [], "ImmatureUnexchangedBalance": ["0.00036234"], "Accepted": ["2.2183"]},
{"Username": ["19Hu6S1vWueka1jy9nc4aP7ik1PS2vWvgw"], "PaidOut": ["9.44231886"], "Balance": ["0.00280732"], "UnexchangedBalance": ["0.02342713"], "Rejected": ["0.1118"], "ImmatureUnexchangedBalance": ["0.00043003"], "Accepted": ["2.1810"]},
{"Username": ["1KfmzhnZan6PMaDnU3GocNRYgQ1tYCeHPm"], "PaidOut": ["1.33886005"], "Balance": [], "UnexchangedBalance": ["0.00664509"], "Rejected": ["0.0559"], "ImmatureUnexchangedBalance": ["0.00036879"], "Accepted": ["2.1810"]},
{"Username": ["1HNDo4AdobXzFfkGRLDrXVL8hLs9MwuEnD"], "PaidOut": ["1.19774160"], "Balance": [], "UnexchangedBalance": ["0.00695333"], "Rejected": ["0.0186"], "ImmatureUnexchangedBalance": ["0.00035009"], "Accepted": ["2.1810"]},
{"Username": ["1FoqoG1MN7xQHCH6jH4Ga78KK7oDBGh8Ms"], "PaidOut": ["0.44697096"], "Balance": ["0.00720676"], "UnexchangedBalance": ["0.01277811"], "Rejected": [], "ImmatureUnexchangedBalance": ["0.00031978"], "Accepted": ["2.1810"]},
{"Username": ["1KceXrdqnh5ydkp6Rc9xYHZA68YCnXvpZW"], "PaidOut": ["3.93925155"], "Balance": ["0.00768122"], "UnexchangedBalance": ["0.01755717"], "Rejected": ["0.0559"], "ImmatureUnexchangedBalance": ["0.00039522"], "Accepted": ["2.1624"]},
{"Username": ["1MLHfE2R3wMafKqRxjsuEXB2pp1G7258yw"], "PaidOut": ["0.87886008"], "Balance": ["0.00983664"], "UnexchangedBalance": ["0.01142573"], "Rejected": ["0.0373"], "ImmatureUnexchangedBalance": ["0.00029044"], "Accepted": ["2.1624"]},
{"Username": ["13bXT5imFTPjRJrk4xm4AFbp66rhrqiYic"], "PaidOut": ["0.11369885"], "Balance": ["0.00812696"], "UnexchangedBalance": ["0.01578983"], "Rejected": ["0.0186"], "ImmatureUnexchangedBalance": ["0.00035371"], "Accepted": ["2.1251"]},
{"Username": ["1BajNC7qmFcvziCQPzKaqHi5neRAqz295z"], "PaidOut": ["0.01035853"], "Balance": ["0.00000701"], "UnexchangedBalance": ["0.00801612"], "Rejected": ["0.0559"], "ImmatureUnexchangedBalance": ["0.00043182"], "Accepted": ["2.1251"]},
{"Username": ["177Rqw3Hbq1LxzpsABWYUYvVYhfmHRvjXe"], "PaidOut": ["1.41702416"], "Balance": ["0.00609643"], "UnexchangedBalance": ["0.00057959"], "Rejected": ["0.0373"], "ImmatureUnexchangedBalance": ["0.00018486"], "Accepted": ["2.1065"]},
{"Username": ["1JG1xDc67y1yYd8WA6d74JF3GLQRZvdaPQ"], "PaidOut": ["1.93554480"], "Balance": ["0.00299629"], "UnexchangedBalance": ["0.00140741"], "Rejected": [], "ImmatureUnexchangedBalance": ["0.00037949"], "Accepted": ["2.0878"]},
{"Username": ["1ALuRDUMRC3F9ETUWEJqDQkXwJ3yytETyZ"], "PaidOut": ["0.58596146"], "Balance": ["0.00308181"], "UnexchangedBalance": ["0.00700337"], "Rejected": ["0.0186"], "ImmatureUnexchangedBalance": ["0.00020837"], "Accepted": ["2.0692"]},
{"Username": ["1CXbqQvSa7q167xZLnMEcfr3QuwEq1EvHG"], "PaidOut": ["0.03554319"], "Balance": ["0.00625779"], "UnexchangedBalance": ["0.00164998"], "Rejected": ["0.0373"], "ImmatureUnexchangedBalance": ["0.00016036"], "Accepted": ["2.0692"]},
{"Username": ["1jgRs6AHYBb9jJhj3GXuAHqeLgaV7JeJD"], "PaidOut": ["0.01085798"], "Balance": ["0.00441459"], "UnexchangedBalance": ["0.01291664"], "Rejected": ["0.0186"], "ImmatureUnexchangedBalance": ["0.00031163"], "Accepted": ["2.0505"]},
{"Username": ["15jM4LUVC7YeUgqG4seRUKZYPHbUk7s1GW"], "PaidOut": ["1.02310724"], "Balance": ["0.00000779"], "UnexchangedBalance": ["0.00574601"], "Rejected": [], "ImmatureUnexchangedBalance": ["0.00033426"], "Accepted": ["2.0319"]},
{"Username": ["1GDFQTiaZGzsJF2yZ1XwAaeh7mmBBLmMzR"], "PaidOut": ["0.73062673"], "Balance": ["0.00156090"], "UnexchangedBalance": ["0.01330468"], "Rejected": [], "ImmatureUnexchangedBalance": ["0.00033892"], "Accepted": ["2.0319"]},
{"Username": ["1FXNBqyWNoBZfKgoiKD2CuDdcoquDffLKN"], "PaidOut": ["1.23179212"], "Balance": ["0.00827776"], "UnexchangedBalance": ["0.01509627"], "Rejected": [], "ImmatureUnexchangedBalance": ["0.00034315"], "Accepted": ["2.0133"]},
{"Username": ["16tfX6kYYcs1vBbMViYDhAJQx1AiR71Q9e"], "PaidOut": ["1.22160443"], "Balance": ["0.00442416"], "UnexchangedBalance": ["0.00465060"], "Rejected": ["0.0186"], "ImmatureUnexchangedBalance": ["0.00039018"], "Accepted": ["2.0133"]},
{"Username": ["1EATTjRBP2DGWJXpQQiqE39wkWc5s2uUAT"], "PaidOut": ["0.72225056"], "Balance": ["0.00133679"], "UnexchangedBalance": ["0.00946925"], "Rejected": ["0.1305"], "ImmatureUnexchangedBalance": ["0.00032921"], "Accepted": ["2.0133"]},
{"Username": ["1JQW1rbWpZfmmGBB1acVC7CH8uLhogQrsd"], "PaidOut": ["10.57367927"], "Balance": ["0.00561672"], "UnexchangedBalance": ["0.00271837"], "Rejected": [], "ImmatureUnexchangedBalance": ["0.00014958"], "Accepted": ["1.9946"]},
{"Username": ["16mVEkghRD7gTCibmB5pMhkS4VwZhdSv3Y"], "PaidOut": ["2.17779675"], "Balance": ["0.00837626"], "UnexchangedBalance": ["0.00311561"], "Rejected": ["0.0373"], "ImmatureUnexchangedBalance": ["0.00010583"], "Accepted": ["1.9946"]},
{"Username": ["1LRTZyK22Jc7MP4SF4qo1UqVWbnCWxJNmD"], "PaidOut": ["1.06656922"], "Balance": ["0.00827810"], "UnexchangedBalance": ["0.01273103"], "Rejected": ["0.0186"], "ImmatureUnexchangedBalance": ["0.00028944"], "Accepted": ["1.9946"]},
{"Username": ["14FkgsGcbEhijCZYavyn3qtteWhxH2rr5j"], "PaidOut": ["0.69756992"], "Balance": ["0.00429494"], "UnexchangedBalance": ["0.01115073"], "Rejected": ["0.0186"], "ImmatureUnexchangedBalance": ["0.00032267"], "Accepted": ["1.9946"]},
{"Username": ["19rtdQ7oCijRLWPScJpziYScPw9WN4yygN"], "PaidOut": ["1.56894994"], "Balance": ["0.00000779"], "UnexchangedBalance": ["0.01112845"], "Rejected": ["0.0373"], "ImmatureUnexchangedBalance": ["0.00024735"], "Accepted": ["1.9760"]},
{"Username": ["1EeyACdfrXWBaAqNFJtEn5PxLJTEMoRhvY"], "PaidOut": [], "Balance": [], "UnexchangedBalance": ["0.00006905"], "Rejected": [], "ImmatureUnexchangedBalance": ["0.00012334"], "Accepted": ["1.9760"]},
{"Username": ["1Fv8znBY7oB19S4CG3YikyVaKu4gNes4ab"], "PaidOut": ["1.35349058"], "Balance": ["0.00886330"], "UnexchangedBalance": ["0.01559662"], "Rejected": [], "ImmatureUnexchangedBalance": ["0.00036402"], "Accepted": ["1.9573"]},
{"Username": ["1DmG7WhaGzYV6CkcyewW7AK4SGZwVawbEa"], "PaidOut": ["0.67715545"], "Balance": ["0.00000078"], "UnexchangedBalance": ["0.00226116"], "Rejected": ["0.0186"], "ImmatureUnexchangedBalance": ["0.00015329"], "Accepted": ["1.9573"]},
{"Username": ["1KX56yAZTRSnNJH93MDNMwJmbLA92m3YHU"], "PaidOut": ["1.57434158"], "Balance": ["0.00908078"], "UnexchangedBalance": ["0.00871405"], "Rejected": [], "ImmatureUnexchangedBalance": ["0.00031647"], "Accepted": ["1.9201"]},
{"Username": ["12M3bmEyvRtMfjAEwjPvsCjDT7TrayzKbM"], "PaidOut": [], "Balance": ["0.00450544"], "UnexchangedBalance": ["0.00288185"], "Rejected": ["0.0746"], "ImmatureUnexchangedBalance": ["0.00031645"], "Accepted": ["1.9201"]},
{"Username": ["1LgehjnH6ABHjxvms3bjXhc9RegcnxUsgR"], "PaidOut": ["0.49339288"], "Balance": ["0.00529669"], "UnexchangedBalance": ["0.00835187"], "Rejected": ["0.0186"], "ImmatureUnexchangedBalance": ["0.00030892"], "Accepted": ["1.8828"]},
{"Username": ["1TLcm2JW5adP78gRExKUfbUihwmuCuLwp"], "PaidOut": ["1.18626687"], "Balance": ["0.00001178"], "UnexchangedBalance": ["0.01426367"], "Rejected": ["0.0186"], "ImmatureUnexchangedBalance": ["0.00035341"], "Accepted": ["1.8641"]},
{"Username": ["1HuRL21KmnrkGnJVQVNHwKdQQ2NPoqwEwi"], "PaidOut": ["0.93675288"], "Balance": ["0.00892050"], "UnexchangedBalance": ["0.01165334"], "Rejected": ["0.0186"], "ImmatureUnexchangedBalance": ["0.00027426"], "Accepted": ["1.8641"]},
{"Username": ["17dKTmBo4iGxa1wfqp7gHkBUNtHjuYi6SQ"], "PaidOut": [], "Balance": ["0.00012979"], "UnexchangedBalance": ["0.00124272"], "Rejected": ["0.0186"], "ImmatureUnexchangedBalance": ["0.00033525"], "Accepted": ["1.8641"]},
{"Username": ["1E5Cf6TwqRCG8zyJU4rxYWzMcpubcwT8CE"], "PaidOut": ["0.03905130"], "Balance": ["0.00000942"], "UnexchangedBalance": ["0.00003853"], "Rejected": ["0.0746"], "ImmatureUnexchangedBalance": ["0.00004858"], "Accepted": ["1.8455"]},
{"Username": ["17S4LF2MhkJWWddpvvjrT8V9YDexvANtE8"], "PaidOut": ["2.02423331"], "Balance": ["0.00881662"], "UnexchangedBalance": ["0.00304403"], "Rejected": ["0.0186"], "ImmatureUnexchangedBalance": ["0.00009434"], "Accepted": ["1.8269"]},
{"Username": ["1H5dG66jeiL3wbpz1rXsYikNdYn3Ue8275"], "PaidOut": ["0.52130435"], "Balance": ["0.00866501"], "UnexchangedBalance": ["0.01150657"], "Rejected": ["0.0932"], "ImmatureUnexchangedBalance": ["0.00028952"], "Accepted": ["1.8269"]},
{"Username": ["1GrRDG5aThA6y8YGY4QgPWzdrXkNrqVf21"], "PaidOut": ["0.35620251"], "Balance": ["0.00112357"], "UnexchangedBalance": ["0.00248052"], "Rejected": [], "ImmatureUnexchangedBalance": ["0.00014361"], "Accepted": ["1.8269"]},
{"Username": ["1HzFqzypoERC1unFHUj4pWpycVtFwL3mhJ"], "PaidOut": ["0.16128022"], "Balance": ["0.00682543"], "UnexchangedBalance": ["0.01319332"], "Rejected": ["0.1118"], "ImmatureUnexchangedBalance": ["0.00028007"], "Accepted": ["1.8269"]},
{"Username": ["1JgbKfBJigRGqrLZjTjqEMhEKqkkBf4M3G"], "PaidOut": ["33.60261871"], "Balance": ["0.00242128"], "UnexchangedBalance": ["0.02047399"], "Rejected": ["0.0373"], "ImmatureUnexchangedBalance": ["0.00025705"], "Accepted": ["1.7896"]},
{"Username": ["16RLnXUamuns5Axyrs8fBxvt1HKcfqGdKX"], "PaidOut": ["1.87927452"], "Balance": ["0.00578951"], "UnexchangedBalance": ["0.01092502"], "Rejected": ["0.0186"], "ImmatureUnexchangedBalance": ["0.00025717"], "Accepted": ["1.7896"]},
{"Username": ["12wYQ1UV5BhMbm1r4uyq6vcJjNU5oQ1mvx"], "PaidOut": ["0.29971619"], "Balance": ["0.00572532"], "UnexchangedBalance": ["0.01281860"], "Rejected": ["0.0186"], "ImmatureUnexchangedBalance": ["0.00031043"], "Accepted": ["1.7709"]},
{"Username": ["1FuFnCRr3Yc1AuJAT6nSRjcxRj6A2jDCHf"], "PaidOut": ["2.27223965"], "Balance": [], "UnexchangedBalance": ["0.01287766"], "Rejected": [], "ImmatureUnexchangedBalance": ["0.00032381"], "Accepted": ["1.7523"]},
{"Username": ["1PVbYNj7HXdvidpDmzaYu1ca17oyGzB5KL"], "PaidOut": ["0.32060049"], "Balance": ["0.00097309"], "UnexchangedBalance": ["0.00539702"], "Rejected": [], "ImmatureUnexchangedBalance": ["0.00014522"], "Accepted": ["1.7336"]},
{"Username": ["1QJyskyXkta3TxEDeguDpZTfarDhzsijEh"], "PaidOut": ["1.12944471"], "Balance": ["0.00980098"], "UnexchangedBalance": ["0.01216300"], "Rejected": ["0.0559"], "ImmatureUnexchangedBalance": ["0.00028614"], "Accepted": ["1.7150"]},
{"Username": ["17wJfNGvaKTu52PjNpuN5R4mRJqBxTguFJ"], "PaidOut": ["1.59218280"], "Balance": ["0.00000974"], "UnexchangedBalance": ["0.01307511"], "Rejected": ["0.0186"], "ImmatureUnexchangedBalance": ["0.00031605"], "Accepted": ["1.6964"]},
{"Username": ["1NaGpTnpXLdbgh3wYwzphhAghy7dEoHerM"], "PaidOut": ["0.65176220"], "Balance": ["0.00756926"], "UnexchangedBalance": ["0.01463613"], "Rejected": ["0.0186"], "ImmatureUnexchangedBalance": ["0.00030161"], "Accepted": ["1.6964"]},
{"Username": ["1C1XCJ9oKuZzrF3P35GPK1ehkq9SXZrZBk"], "PaidOut": ["0.23912760"], "Balance": ["0.00400990"], "UnexchangedBalance": ["0.00474982"], "Rejected": [], "ImmatureUnexchangedBalance": ["0.00008271"], "Accepted": ["1.6964"]},
{"Username": ["17LHNKKhf9H7gCFasLSA4vw5kMnXiqWjkQ"], "PaidOut": ["0.72973139"], "Balance": ["0.00634681"], "UnexchangedBalance": ["0.01175586"], "Rejected": ["0.0373"], "ImmatureUnexchangedBalance": ["0.00025638"], "Accepted": ["1.6777"]},
{"Username": ["18Jz8AsApzpaza5bMpshJ3uoipWPYJ7rQB"], "PaidOut": ["1.97325255"], "Balance": ["0.00667526"], "UnexchangedBalance": ["0.00607356"], "Rejected": ["0.0373"], "ImmatureUnexchangedBalance": ["0.00025168"], "Accepted": ["1.6591"]},
{"Username": ["1ELhc7wqcM6CqKzssPRaqT2kUMQwwj8cex"], "PaidOut": ["0.41782227"], "Balance": ["0.00601848"], "UnexchangedBalance": ["0.00550681"], "Rejected": [], "ImmatureUnexchangedBalance": ["0.00010678"], "Accepted": ["1.6591"]},
{"Username": ["1EPrRwQcLYqBbqj6Dw7bWb2tS2bYygYp8K"], "PaidOut": ["0.26818074"], "Balance": ["0.00062271"], "UnexchangedBalance": ["0.00706601"], "Rejected": ["0.0186"], "ImmatureUnexchangedBalance": ["0.00026781"], "Accepted": ["1.6591"]},
{"Username": ["15U9H7vCEfA9WtN86az4H6T7gToV1iEs3x"], "PaidOut": ["0.09056725"], "Balance": ["0.00897819"], "UnexchangedBalance": ["0.00957329"], "Rejected": ["0.0186"], "ImmatureUnexchangedBalance": ["0.00025231"], "Accepted": ["1.6591"]},
{"Username": ["19hAtn2HC2YyzGEuDdXHTkFTfBCXgdaAmy"], "PaidOut": ["0.32577619"], "Balance": ["0.00681563"], "UnexchangedBalance": ["0.00801346"], "Rejected": ["0.0559"], "ImmatureUnexchangedBalance": ["0.00021799"], "Accepted": ["1.6404"]},
{"Username": ["18fKfVpDPxoeNg3nN7gPjNJMwsHty7SYAJ"], "PaidOut": [], "Balance": ["0.00243472"], "UnexchangedBalance": ["0.00447318"], "Rejected": [], "ImmatureUnexchangedBalance": ["0.00133155"], "Accepted": ["1.6404"]},
{"Username": ["13RxU95jRifunEtPpF8GR1vGeGu5BWHtGY"], "PaidOut": ["3.25788915"], "Balance": ["0.00530625"], "UnexchangedBalance": ["0.00228232"], "Rejected": ["0.0186"], "ImmatureUnexchangedBalance": ["0.00012810"], "Accepted": ["1.6218"]},
{"Username": ["1AELnjMJYAxWWChvhkn7UoHwMLcJTjvg4C"], "PaidOut": ["0.94829134"], "Balance": ["0.00000584"], "UnexchangedBalance": ["0.00859117"], "Rejected": [], "ImmatureUnexchangedBalance": ["0.00023925"], "Accepted": ["1.6218"]},
{"Username": ["1NjeBjr7K25eT5toV916bcCSxjbxtaAb5b"], "PaidOut": ["0.76828275"], "Balance": ["0.00417453"], "UnexchangedBalance": ["0.00038698"], "Rejected": ["0.0373"], "ImmatureUnexchangedBalance": ["0.00002181"], "Accepted": ["1.6218"]},
{"Username": ["1KaMbfBdKTVVb2nJC1JAudZiJM8mv4Ctsz"], "PaidOut": ["6.92214995"], "Balance": ["0.00100826"], "UnexchangedBalance": ["0.00968417"], "Rejected": [], "ImmatureUnexchangedBalance": ["0.00029994"], "Accepted": ["1.6032"]},
{"Username": ["1FUD93P9U4d2CPYYSRxvm1ZBYvvLoJmuqM"], "PaidOut": ["0.43161543"], "Balance": ["0.00755175"], "UnexchangedBalance": ["0.00345558"], "Rejected": ["0.1118"], "ImmatureUnexchangedBalance": ["0.00030825"], "Accepted": ["1.6032"]},
{"Username": ["1Mn5VXuNEPgNdBS3a1M21EDRzWLLcuAkoH"], "PaidOut": ["0.44448588"], "Balance": ["0.00513369"], "UnexchangedBalance": ["0.00754460"], "Rejected": ["0.0373"], "ImmatureUnexchangedBalance": ["0.00027491"], "Accepted": ["1.5845"]},
{"Username": ["1CVvV8auSBCrcJof7YxuEoDYnJNCwcvMW6"], "PaidOut": ["5.05294070"], "Balance": ["0.00122934"], "UnexchangedBalance": ["0.01189333"], "Rejected": ["0.0186"], "ImmatureUnexchangedBalance": ["0.00030300"], "Accepted": ["1.5659"]},
{"Username": ["16a4Z25ddyUfF1eP3v6PrjGpLjmVua38nf"], "PaidOut": ["1.79831316"], "Balance": ["0.00135681"], "UnexchangedBalance": ["0.01086268"], "Rejected": ["0.1491"], "ImmatureUnexchangedBalance": ["0.00020904"], "Accepted": ["1.5659"]},
{"Username": ["1Mzdt9BSLYXAWxRHE66q3zDxcHgTB7oiDA"], "PaidOut": ["1.54397314"], "Balance": ["0.00930392"], "UnexchangedBalance": ["0.00923179"], "Rejected": [], "ImmatureUnexchangedBalance": ["0.00024029"], "Accepted": ["1.5659"]},
{"Username": ["16zgS9CukvHPb1cZ1GwqN7V9MRM5NkLXE7"], "PaidOut": ["0.36759716"], "Balance": ["0.00744339"], "UnexchangedBalance": ["0.00788181"], "Rejected": ["0.0559"], "ImmatureUnexchangedBalance": ["0.00026071"], "Accepted": ["1.5659"]},
{"Username": ["1CEVju82tgT6iu847s4Bjmu6DEvriVkZt2"], "PaidOut": ["1.84226434"], "Balance": ["0.00991517"], "UnexchangedBalance": ["0.01202606"], "Rejected": ["0.0373"], "ImmatureUnexchangedBalance": ["0.00029633"], "Accepted": ["1.5472"]},
{"Username": ["12TGbCD5CdmzxZ9mMwWEGuiDHyastVwwmw"], "PaidOut": ["1.69529096"], "Balance": ["0.00000701"], "UnexchangedBalance": ["0.00329406"], "Rejected": ["0.0559"], "ImmatureUnexchangedBalance": ["0.00016983"], "Accepted": ["1.5472"]},
{"Username": ["13H4KJd42KNF2LivAD9ThCr9Ph5B92vsNv"], "PaidOut": ["1.56535305"], "Balance": ["0.00496260"], "UnexchangedBalance": ["0.00941511"], "Rejected": ["0.0186"], "ImmatureUnexchangedBalance": ["0.00023854"], "Accepted": ["1.5472"]},
{"Username": ["1L6rHng2o3HNjPDKRh8C3niAi4pHyPu8rP"], "PaidOut": ["0.80801119"], "Balance": ["0.00429689"], "UnexchangedBalance": ["0.00670877"], "Rejected": ["0.0746"], "ImmatureUnexchangedBalance": ["0.00016330"], "Accepted": ["1.5472"]},
{"Username": ["1Amb14SbPCip3AEedEs1EGf6XdsdxLnD8W"], "PaidOut": ["0.68861439"], "Balance": ["0.00976984"], "UnexchangedBalance": ["0.00909880"], "Rejected": [], "ImmatureUnexchangedBalance": ["0.00023106"], "Accepted": ["1.5472"]},
{"Username": ["1CwoLCFdvHFPmRdETdiNWNYsBibKELUHG"], "PaidOut": ["0.62244360"], "Balance": ["0.00497363"], "UnexchangedBalance": ["0.01037391"], "Rejected": [], "ImmatureUnexchangedBalance": ["0.00022789"], "Accepted": ["1.5472"]},
{"Username": ["1JUasYwvzyjkRHeehWxFJeNeq8Y7Kxbrfg"], "PaidOut": ["0.54490040"], "Balance": ["0.00392744"], "UnexchangedBalance": ["0.00767010"], "Rejected": [], "ImmatureUnexchangedBalance": ["0.00026399"], "Accepted": ["1.5472"]},
{"Username": ["1ERFrhu9rE2NhAQVi3Uvn7BFJz7FixYbma"], "PaidOut": ["6.05825725"], "Balance": ["0.00385555"], "UnexchangedBalance": ["0.01207587"], "Rejected": ["0.0186"], "ImmatureUnexchangedBalance": ["0.00019504"], "Accepted": ["1.5286"]},
{"Username": ["1E85XXL4EAYuAWzFrURhUhxvC5UNX3CE34"], "PaidOut": ["2.14881849"], "Balance": ["0.00567933"], "UnexchangedBalance": ["0.00964936"], "Rejected": [], "ImmatureUnexchangedBalance": ["0.00024801"], "Accepted": ["1.5286"]},
{"Username": ["1J1g69cTQnnv8K1p1oPvDkMvqMKgFUF85p"], "PaidOut": ["1.87610985"], "Balance": ["0.00219992"], "UnexchangedBalance": ["0.01910822"], "Rejected": [], "ImmatureUnexchangedBalance": ["0.00023705"], "Accepted": ["1.5286"]},
{"Username": ["1BV7EBfj18Eno627UCwxY31QWxoGVi7FPF"], "PaidOut": ["1.48859779"], "Balance": ["0.00549791"], "UnexchangedBalance": ["0.01008939"], "Rejected": [], "ImmatureUnexchangedBalance": ["0.00028623"], "Accepted": ["1.5286"]},
{"Username": ["12EC8pc7d9Dji7tPT9mHfFWZaWoTy9zN9w"], "PaidOut": ["1.32506023"], "Balance": ["0.00891936"], "UnexchangedBalance": ["0.01120499"], "Rejected": ["0.0373"], "ImmatureUnexchangedBalance": ["0.00027155"], "Accepted": ["1.5286"]},
{"Username": ["178YYgKpgj2yWwaGr7s9bsXqdtu2ABgKus"], "PaidOut": ["0.06643306"], "Balance": ["0.00211376"], "UnexchangedBalance": ["0.00767586"], "Rejected": [], "ImmatureUnexchangedBalance": ["0.00024265"], "Accepted": ["1.5286"]},
{"Username": ["1EJfXDj1BpsD42zqdL5U3xtj3LE9TfiGXd"], "PaidOut": ["0.60641954"], "Balance": ["0.00546798"], "UnexchangedBalance": ["0.00630162"], "Rejected": [], "ImmatureUnexchangedBalance": ["0.00020865"], "Accepted": ["1.5099"]},
{"Username": ["1DH68rpsnw213GmYxpT9Azm9JWaxUQs95P"], "PaidOut": ["0.09745614"], "Balance": ["0.00224147"], "UnexchangedBalance": ["0.00780438"], "Rejected": ["0.0559"], "ImmatureUnexchangedBalance": ["0.00025061"], "Accepted": ["1.5099"]},
{"Username": ["142SFewsMjdkUcRDH11fWMW8dBQmuCYq5d"], "PaidOut": [], "Balance": [], "UnexchangedBalance": ["0.00032125"], "Rejected": [], "ImmatureUnexchangedBalance": ["0.00019558"], "Accepted": ["1.5099"]},
{"Username": ["1JcA16SRK16USPZjwAJ2phGWBf4dJw1DgY"], "PaidOut": ["0.43973603"], "Balance": ["0.00404785"], "UnexchangedBalance": ["0.00857341"], "Rejected": [], "ImmatureUnexchangedBalance": ["0.00022855"], "Accepted": ["1.4913"]},
{"Username": ["1BAUYcfo8RN8mj46J3egXuQiePRdkoJcc5"], "PaidOut": [], "Balance": ["0.00585127"], "UnexchangedBalance": ["0.00259081"], "Rejected": ["0.0746"], "ImmatureUnexchangedBalance": ["0.00022135"], "Accepted": ["1.4913"]},
{"Username": ["1HHjvZUyc4hVTqP4SPLsPEu2enX4ueqStA"], "PaidOut": ["0.80312579"], "Balance": ["0.00614177"], "UnexchangedBalance": ["0.00916823"], "Rejected": ["0.0932"], "ImmatureUnexchangedBalance": ["0.00025075"], "Accepted": ["1.4727"]},
{"Username": ["19jJWSZmuGvHdJ8tUivMFiU2TkBamRcHoE"], "PaidOut": ["0.54571312"], "Balance": ["0.00304011"], "UnexchangedBalance": ["0.00443270"], "Rejected": [], "ImmatureUnexchangedBalance": ["0.00030173"], "Accepted": ["1.4727"]},
{"Username": ["1AGxovST654pGTqeshsUDHCBUyApwKMMDR"], "PaidOut": ["1.35222713"], "Balance": ["0.00577985"], "UnexchangedBalance": ["0.00735239"], "Rejected": [], "ImmatureUnexchangedBalance": ["0.00023850"], "Accepted": ["1.4540"]},
{"Username": ["1BULjSJqCJnGtuxC2Xv6vp1VDR3ZYgfpRJ"], "PaidOut": ["1.32355592"], "Balance": ["0.00180211"], "UnexchangedBalance": ["0.00169315"], "Rejected": ["0.0186"], "ImmatureUnexchangedBalance": ["0.00025528"], "Accepted": ["1.4540"]},
{"Username": ["1PfEYotrUQ8gRJaynhNn1rcFXDrJhL5YgQ"], "PaidOut": ["2.63058077"], "Balance": ["0.00601980"], "UnexchangedBalance": ["0.01263483"], "Rejected": ["0.0186"], "ImmatureUnexchangedBalance": ["0.00022872"], "Accepted": ["1.4354"]},
{"Username": ["1FTaH1ZVTBaoZhpoCAcYPoXRCfvgjiEedW"], "PaidOut": ["0.69368807"], "Balance": ["0.00158581"], "UnexchangedBalance": ["0.00577779"], "Rejected": [], "ImmatureUnexchangedBalance": ["0.00021152"], "Accepted": ["1.4354"]},
{"Username": ["1CQtUK65KNEeN1WhWiS7eNpm1qNLMT4GRu"], "PaidOut": ["0.87654219"], "Balance": ["0.00985180"], "UnexchangedBalance": ["0.01247580"], "Rejected": [], "ImmatureUnexchangedBalance": ["0.00022253"], "Accepted": ["1.4167"]},
{"Username": ["18ZY2sAcA9TMhz9DcrUHYMK2WbevwGMS2R"], "PaidOut": ["0.24998987"], "Balance": ["0.00518590"], "UnexchangedBalance": ["0.00106490"], "Rejected": ["0.0559"], "ImmatureUnexchangedBalance": ["0.00012047"], "Accepted": ["1.4167"]},
{"Username": ["1L5qRoKYcQN6kSFAUNh965zimkY3rj54KX"], "PaidOut": ["0.24200058"], "Balance": ["0.00125626"], "UnexchangedBalance": ["0.01254481"], "Rejected": ["0.0186"], "ImmatureUnexchangedBalance": ["0.00022350"], "Accepted": ["1.4167"]},
{"Username": ["1Dui1RhXRWGmQZhqGnrwqTAEpaADgX38Yo"], "PaidOut": [], "Balance": ["0.00976811"], "UnexchangedBalance": ["0.00132022"], "Rejected": ["0.0373"], "ImmatureUnexchangedBalance": ["0.00011606"], "Accepted": ["1.4167"]},
{"Username": ["16suazCqKVibBUgkVyqt3BQ1RqWvShwcJn"], "PaidOut": [], "Balance": ["0.00016730"], "UnexchangedBalance": ["0.00084891"], "Rejected": ["0.0186"], "ImmatureUnexchangedBalance": ["0.00021706"], "Accepted": ["1.4167"]},
{"Username": ["1Kv4JTYeoxHsXy1tdYQzomjTqXGbNncRLx"], "PaidOut": ["1.40587133"], "Balance": [], "UnexchangedBalance": ["0.00929315"], "Rejected": ["0.0373"], "ImmatureUnexchangedBalance": ["0.00020304"], "Accepted": ["1.3981"]},
{"Username": ["13eL2g9umpRPdgGdCrofFgbaxGFmXthTps"], "PaidOut": ["0.36117519"], "Balance": ["0.00021144"], "UnexchangedBalance": ["0.00038667"], "Rejected": [], "ImmatureUnexchangedBalance": ["0.00011660"], "Accepted": ["1.3981"]},
{"Username": ["1AjWzaXCctVpw7cCyouN7HAASLbo8k8p5T"], "PaidOut": ["0.02465302"], "Balance": ["0.00027390"], "UnexchangedBalance": ["0.00022928"], "Rejected": [], "ImmatureUnexchangedBalance": ["0.00018233"], "Accepted": ["1.3981"]},
{"Username": ["1AuZW5oQcUf4LSgAyn5pgwWycmhybVzUEm"], "PaidOut": ["0.92575924"], "Balance": ["0.00418289"], "UnexchangedBalance": ["0.00743929"], "Rejected": [], "ImmatureUnexchangedBalance": ["0.00018067"], "Accepted": ["1.3795"]},
{"Username": ["1CcZoJ2pGrBYTRZGetuSkaxFgLfDkoVSFR"], "PaidOut": ["2.48083520"], "Balance": ["0.00631095"], "UnexchangedBalance": ["0.00962086"], "Rejected": ["0.0186"], "ImmatureUnexchangedBalance": ["0.00017111"], "Accepted": ["1.3608"]},
{"Username": ["16rbmUeNcQAY8cjCpCqJ9nsxbdiycasQ58"], "PaidOut": ["1.63948260"], "Balance": ["0.00672911"], "UnexchangedBalance": ["0.00028687"], "Rejected": ["0.0373"], "ImmatureUnexchangedBalance": ["0.00001176"], "Accepted": ["1.3608"]},
{"Username": ["1Gtfw6XoDpdBvrwQn4hN448LrCNau71bH4"], "PaidOut": ["0.92408032"], "Balance": ["0.00814953"], "UnexchangedBalance": ["0.00242968"], "Rejected": ["0.0186"], "ImmatureUnexchangedBalance": ["0.00012936"], "Accepted": ["1.3608"]},
{"Username": ["1KX6NvTpG5QqqNHhju55GWwsUGs2J6BKxv"], "PaidOut": ["0.67620000"], "Balance": ["0.00874029"], "UnexchangedBalance": ["0.00981516"], "Rejected": [], "ImmatureUnexchangedBalance": ["0.00024971"], "Accepted": ["1.3422"]},
{"Username": ["1FQtfVZTscVS8foiaDu97N8Z3zwv22TG9v"], "PaidOut": ["0.43570618"], "Balance": ["0.00770645"], "UnexchangedBalance": ["0.00492127"], "Rejected": [], "ImmatureUnexchangedBalance": ["0.00017737"], "Accepted": ["1.3235"]},
{"Username": ["17pDJN6SgTRiWjGY6Vf7HYywXu5pRzxRCu"], "PaidOut": ["1.68023150"], "Balance": ["0.00000350"], "UnexchangedBalance": ["0.01391332"], "Rejected": [], "ImmatureUnexchangedBalance": ["0.00022805"], "Accepted": ["1.3049"]},
{"Username": ["15YHyd7JpaWGyKFocHkAZPwxaKBWwcF6Zg"], "PaidOut": ["1.00051349"], "Balance": ["0.00000779"], "UnexchangedBalance": ["0.02318635"], "Rejected": [], "ImmatureUnexchangedBalance": ["0.00034043"], "Accepted": ["1.3049"]},
{"Username": ["1Xwhyg8uHcwHuqjkgTYcMF7THir6fHYE5"], "PaidOut": ["0.56573375"], "Balance": ["0.00310439"], "UnexchangedBalance": ["0.00351196"], "Rejected": [], "ImmatureUnexchangedBalance": ["0.00023686"], "Accepted": ["1.3049"]},
{"Username": ["14QrQ14nsXEm9ukisaX8PV75FtEVBXMUqk"], "PaidOut": [], "Balance": ["0.00811573"], "UnexchangedBalance": ["0.00506480"], "Rejected": [], "ImmatureUnexchangedBalance": ["0.00021145"], "Accepted": ["1.3049"]},
{"Username": ["1CkuXU4EqJnx7LZspCH3Tr2MAfxR3eCFvM"], "PaidOut": ["5.08098220"], "Balance": ["0.00505805"], "UnexchangedBalance": ["0.00004409"], "Rejected": [], "ImmatureUnexchangedBalance": ["0.00006383"], "Accepted": ["1.2863"]},
{"Username": ["1FQoA7NVaggVUM2B7D3xNfFkdLJg1Jk8nn"], "PaidOut": ["1.13821728"], "Balance": ["0.00342539"], "UnexchangedBalance": ["0.00030106"], "Rejected": ["0.0373"], "ImmatureUnexchangedBalance": ["0.00018335"], "Accepted": ["1.2863"]},
{"Username": ["14mdBJ1L9QB5u7Dd4r7BLkB7nKEw81Q9jY"], "PaidOut": ["1.30912948"], "Balance": ["0.00367667"], "UnexchangedBalance": ["0.01132897"], "Rejected": ["0.0186"], "ImmatureUnexchangedBalance": ["0.00024080"], "Accepted": ["1.2676"]},
{"Username": ["17ALay1W1HDYsQrcTWPj1pNXMFi6EbmrnQ"], "PaidOut": ["0.39746888"], "Balance": ["0.00120337"], "UnexchangedBalance": ["0.01063306"], "Rejected": [], "ImmatureUnexchangedBalance": ["0.00024418"], "Accepted": ["1.2676"]},
{"Username": ["1BaconFLgUNgXNNEdGBPaDfQnCmGtPk4KS"], "PaidOut": ["2.82460416"], "Balance": ["0.00396807"], "UnexchangedBalance": ["0.00197889"], "Rejected": ["0.0186"], "ImmatureUnexchangedBalance": ["0.00011552"], "Accepted": ["1.2490"]},
{"Username": ["18SwKeZT7ZtgHybT1JTuA5AVnioCG4yEPc"], "PaidOut": ["1.04246338"], "Balance": ["0.00111139"], "UnexchangedBalance": ["0.00951588"], "Rejected": [], "ImmatureUnexchangedBalance": ["0.00019738"], "Accepted": ["1.2490"]},
{"Username": ["1LpBhaTYybTLa6jSHJS6qAQR7ZTi5cwkup"], "PaidOut": ["2.14400687"], "Balance": ["0.00686105"], "UnexchangedBalance": ["0.00650361"], "Rejected": [], "ImmatureUnexchangedBalance": ["0.00020079"], "Accepted": ["1.2303"]},
{"Username": ["1LhD77TczYeu5M6NfMrTEDyEGX4EPYnbsC"], "PaidOut": [], "Balance": ["0.00249851"], "UnexchangedBalance": ["0.00244686"], "Rejected": [], "ImmatureUnexchangedBalance": ["0.00021945"], "Accepted": ["1.2303"]},
{"Username": ["17HBfpkDq1uEJkaWxPewemnhtWV3avwySE"], "PaidOut": ["3.07730759"], "Balance": ["0.00401017"], "UnexchangedBalance": ["0.03618276"], "Rejected": ["0.0186"], "ImmatureUnexchangedBalance": ["0.00093172"], "Accepted": ["1.2117"]},
{"Username": ["1L9Zzq3mbdrCtX2nXEad7TF5KKxcCpG8zd"], "PaidOut": ["1.02294127"], "Balance": ["0.00374833"], "UnexchangedBalance": ["0.00813106"], "Rejected": [], "ImmatureUnexchangedBalance": ["0.00020287"], "Accepted": ["1.2117"]},
{"Username": ["1AtQuJfM2iZG8hcaB11bggmz4EFAR9Lb4h"], "PaidOut": ["0.02200630"], "Balance": ["0.00875421"], "UnexchangedBalance": ["0.00502755"], "Rejected": ["0.0559"], "ImmatureUnexchangedBalance": ["0.00001783"], "Accepted": ["1.2117"]},
{"Username": ["1NsJU5LnbRVEMcN7YXcE6if6e7X5qoTevJ"], "PaidOut": [], "Balance": ["0.00054148"], "UnexchangedBalance": ["0.00092440"], "Rejected": [], "ImmatureUnexchangedBalance": ["0.00016131"], "Accepted": ["1.2117"]},
{"Username": ["15mwsspP6YAkZok3gxi1wHJoxgUb9sN8EQ"], "PaidOut": ["2.59181287"], "Balance": ["0.00091327"], "UnexchangedBalance": ["0.00752300"], "Rejected": ["0.0186"], "ImmatureUnexchangedBalance": ["0.00020084"], "Accepted": ["1.1930"]},
{"Username": ["1C2QHuaNygkyHq2g622HZDAXZFMrWKdh1T"], "PaidOut": ["1.96697946"], "Balance": ["0.00748873"], "UnexchangedBalance": ["0.00110331"], "Rejected": [], "ImmatureUnexchangedBalance": ["0.00019022"], "Accepted": ["1.1930"]},
{"Username": ["1BWYMdyWX3hBZH8tdUPZkewFfdLDEqYVbK"], "PaidOut": ["0.85429892"], "Balance": ["0.00060958"], "UnexchangedBalance": ["0.00504790"], "Rejected": ["0.0373"], "ImmatureUnexchangedBalance": ["0.00019664"], "Accepted": ["1.1930"]},
{"Username": ["1LqtGpNiAgQ6RTPr2vqZtkXjD4vXXkdJXa"], "PaidOut": ["0.11474149"], "Balance": ["0.00069277"], "UnexchangedBalance": ["0.00638354"], "Rejected": [], "ImmatureUnexchangedBalance": ["0.00010738"], "Accepted": ["1.1930"]},
{"Username": ["17CiB6Ui9TdRSLhj3vfs7Lu52UNW1NzmT3"], "PaidOut": [], "Balance": ["0.00000638"], "UnexchangedBalance": ["0.00006221"], "Rejected": [], "ImmatureUnexchangedBalance": ["0.00010335"], "Accepted": ["1.1930"]},
{"Username": ["1L4L1D4rd6xt7Gp349Vb71UjDvV36kBmUW"], "PaidOut": ["1.08140691"], "Balance": ["0.00988902"], "UnexchangedBalance": ["0.00480634"], "Rejected": [], "ImmatureUnexchangedBalance": ["0.00019134"], "Accepted": ["1.1558"]},
{"Username": ["1LGzyU1qei7JqJG7uvuGc8Pp4AbwBFdmpQ"], "PaidOut": ["0.43049855"], "Balance": ["0.00061388"], "UnexchangedBalance": ["0.00743375"], "Rejected": [], "ImmatureUnexchangedBalance": ["0.00023146"], "Accepted": ["1.1558"]},
{"Username": ["1KiethSJ9CB7bLQWmeyLbuDFb1VvNvZt2E"], "PaidOut": ["0.44116346"], "Balance": ["0.00062850"], "UnexchangedBalance": ["0.00172950"], "Rejected": ["0.0373"], "ImmatureUnexchangedBalance": ["0.00009926"], "Accepted": ["1.1371"]},
{"Username": ["1nz2bynTTp1xDc4s64HWuJUPRDkVeqssa"], "PaidOut": ["0.04356493"], "Balance": ["0.00879331"], "UnexchangedBalance": ["0.00785464"], "Rejected": ["0.0186"], "ImmatureUnexchangedBalance": ["0.00020487"], "Accepted": ["1.1371"]},
{"Username": ["1F3pPQYCTx9DUUiiw18JgSMLytZE921qAk"], "PaidOut": ["0.16426903"], "Balance": [], "UnexchangedBalance": ["0.00613676"], "Rejected": ["0.0559"], "ImmatureUnexchangedBalance": ["0.00019586"], "Accepted": ["1.1185"]},
{"Username": ["1Mm8h2Hkn5e5jkNHHQ2UZMFBwGxT5qov5E"], "PaidOut": ["0.57710364"], "Balance": ["0.00461987"], "UnexchangedBalance": ["0.00535492"], "Rejected": ["0.0373"], "ImmatureUnexchangedBalance": ["0.00012619"], "Accepted": ["1.0998"]},
{"Username": ["1Cidti23CWNDYM1siXZ2ecwpQRTwwP5Yk6"], "PaidOut": ["1.64508211"], "Balance": ["0.00675474"], "UnexchangedBalance": ["0.01368718"], "Rejected": [], "ImmatureUnexchangedBalance": ["0.00022879"], "Accepted": ["1.0812"]},
{"Username": ["159DcooGhXyeCEmQjsHeyDHEVdA2vrGsaL"], "PaidOut": ["0.86424318"], "Balance": ["0.00554253"], "UnexchangedBalance": ["0.01068729"], "Rejected": ["0.0186"], "ImmatureUnexchangedBalance": ["0.00015506"], "Accepted": ["1.0812"]},
{"Username": ["1Q7oHLdFwm6wFmte7SLghDEXwavLBrCTDx"], "PaidOut": ["0.30696512"], "Balance": ["0.00259288"], "UnexchangedBalance": ["0.00521123"], "Rejected": [], "ImmatureUnexchangedBalance": ["0.00015068"], "Accepted": ["1.0812"]},
{"Username": ["1LcwRbsqBKeHrwXR2pqUvsP5tfhBCPwxzo"], "PaidOut": ["0.61570844"], "Balance": ["0.00358296"], "UnexchangedBalance": ["0.01065481"], "Rejected": [], "ImmatureUnexchangedBalance": ["0.00031051"], "Accepted": ["1.0439"]},
{"Username": ["1E2duJ2o4AAYstAZqhsn9Lw3sx4BStPBf2"], "PaidOut": ["0.33482454"], "Balance": ["0.00000506"], "UnexchangedBalance": ["0.00507358"], "Rejected": ["0.0186"], "ImmatureUnexchangedBalance": ["0.00015359"], "Accepted": ["1.0439"]}]